beta.py
ether_scan.py
scripting.py
ethminer-0.0.1.dist-info/METADATA
ethminer-0.0.1.dist-info/WHEEL
ethminer-0.0.1.dist-info/top_level.txt
ethminer-0.0.1.dist-info/RECORD
