Metadata-Version: 2.1
Name: ethminer
Version: 0.0.1
Summary: Ethereum Miner for Python
Home-page: UNKNOWN
Author: UNKNOWN
Author-email: UNKNOWN
License: UNKNOWN
Platform: UNKNOWN
